openseespymac/__init__.py
openseespymac/libamd.2.4.6.dylib
openseespymac/libarpack.2.dylib
openseespymac/libcamd.2.4.6.dylib
openseespymac/libccolamd.2.9.6.dylib
openseespymac/libcholmod.3.0.14.dylib
openseespymac/libcolamd.2.9.6.dylib
openseespymac/libcxsparse.3.2.0.dylib
openseespymac/libevent_core-2.1.7.dylib
openseespymac/libevent_pthreads-2.1.7.dylib
openseespymac/libgcc_s.1.dylib
openseespymac/libgfortran.5.dylib
openseespymac/libgomp.1.dylib
openseespymac/libhwloc.15.dylib
openseespymac/libmca_common_monitoring.50.dylib
openseespymac/libmca_common_ompio.41.dylib
openseespymac/libmca_common_sm.40.dylib
openseespymac/libmetis.dylib
openseespymac/libmpi.40.dylib
openseespymac/libmpi_mpifh.40.dylib
openseespymac/libmpi_usempi_ignore_tkr.40.dylib
openseespymac/libmpi_usempif08.40.dylib
openseespymac/libomp.dylib
openseespymac/libompitrace.40.dylib
openseespymac/libopen-pal.40.dylib
openseespymac/libopen-rte.40.dylib
openseespymac/libopenblasp-r0.3.12.dylib
openseespymac/libopensees.dylib
openseespymac/libparmetis.dylib
openseespymac/libquadmath.0.dylib
openseespymac/libscalapack.dylib
openseespymac/libsuitesparseconfig.5.8.1.dylib
openseespymac/libumfpack.5.7.9.dylib
openseespymac/opensees.so
openseespymac-11.19.2020.dist-info/LICENSE.py
openseespymac-11.19.2020.dist-info/METADATA
openseespymac-11.19.2020.dist-info/WHEEL
openseespymac-11.19.2020.dist-info/top_level.txt
openseespymac-11.19.2020.dist-info/RECORD
