Metadata-Version: 2.1
Name: openseespymac
Version: 11.19.2020
Summary: The Mac OS version of OpenSeesPy
Home-page: UNKNOWN
Author: Stevan Gavrilovic
Author-email: gavrilovic@berkeley.edu
License: UNKNOWN
Platform: UNKNOWN
Classifier: Programming Language :: Python :: 3.8
Classifier: Programming Language :: Python :: 3.9
Classifier: Operating System :: MacOS
Requires-Python: >=3.8
